lurk/__init__.py
lurk/__main__.py
lurk/cli.py
lurk/config.py
lurk/http_client.py
lurk/lurk.py
lurk/misc.py
lurk/models.py
lurk/checkers/__init__.py
lurk/checkers/best_buy.py
lurk/checkers/checker.py
lurk/checkers/memory_express.py
lurk/notifiers/telegram.py
lurk_cli-0.1.7.dist-info/METADATA
lurk_cli-0.1.7.dist-info/WHEEL
lurk_cli-0.1.7.dist-info/entry_points.txt
lurk_cli-0.1.7.dist-info/licenses/LICENSE
lurk_cli-0.1.7.dist-info/RECORD
