Metadata-Version: 2.4
Name: lurk-cli
Version: 0.1.7
Summary: A CLI tool to check product stock across multiple stores.
Project-URL: Homepage, https://github.com/rdmm123/lurk
Author-email: Robert Martinez <rdmm404@gmail.com>
License-Expression: MIT
License-File: LICENSE
Classifier: Development Status :: 3 - Alpha
Classifier: Intended Audience :: Developers
Classifier: License :: OSI Approved :: MIT License
Classifier: Operating System :: OS Independent
Classifier: Programming Language :: Python :: 3
Classifier: Topic :: Utilities
Requires-Python: >=3.13
Requires-Dist: aiogram>=3.18.0
Requires-Dist: beautifulsoup4>=4.13.3
Requires-Dist: curl-cffi>=0.10.0
Requires-Dist: nodriver>=0.39
Requires-Dist: pydantic>=2.10.6
Requires-Dist: pyyaml>=6.0.2
Requires-Dist: requests>=2.32.3
Requires-Dist: rich>=13.9.4
Requires-Dist: typer>=0.15.1
Requires-Dist: types-pyyaml>=6.0.12.20241230
